LICENSE
README.rst
requirements.txt
setup.py
python_by_contract_corpus/__init__.py
python_by_contract_corpus/common.py
python_by_contract_corpus/py.typed
python_by_contract_corpus.egg-info/PKG-INFO
python_by_contract_corpus.egg-info/SOURCES.txt
python_by_contract_corpus.egg-info/dependency_links.txt
python_by_contract_corpus.egg-info/requires.txt
python_by_contract_corpus.egg-info/top_level.txt
python_by_contract_corpus/aoc2020/__init__.py
python_by_contract_corpus/aoc2020/day_10_adapter_array.py
python_by_contract_corpus/aoc2020/day_11_seating_system.py
python_by_contract_corpus/aoc2020/day_12_rain_risk.py
python_by_contract_corpus/aoc2020/day_13_shuttle_search.py
python_by_contract_corpus/aoc2020/day_14_docking_data.py
python_by_contract_corpus/aoc2020/day_15_rambunctious_recitation.py
python_by_contract_corpus/aoc2020/day_16_ticket_translation.py
python_by_contract_corpus/aoc2020/day_17_conway_cubes.py
python_by_contract_corpus/aoc2020/day_18_operation_order.py
python_by_contract_corpus/aoc2020/day_19_monster_messages.py
python_by_contract_corpus/aoc2020/day_1_report_repair.py
python_by_contract_corpus/aoc2020/day_20_jurassic_jigsaw.py
python_by_contract_corpus/aoc2020/day_21_allergen_assessment.py
python_by_contract_corpus/aoc2020/day_22_crab_combat.py
python_by_contract_corpus/aoc2020/day_23_crab_cups.py
python_by_contract_corpus/aoc2020/day_24_lobby_layout.py
python_by_contract_corpus/aoc2020/day_25_combo_breaker.py
python_by_contract_corpus/aoc2020/day_2_password_philosophy.py
python_by_contract_corpus/aoc2020/day_3_toboggan_trajectory.py
python_by_contract_corpus/aoc2020/day_4_passport_processing.py
python_by_contract_corpus/aoc2020/day_5_binary_boarding.py
python_by_contract_corpus/aoc2020/day_6_custom_customs.py
python_by_contract_corpus/aoc2020/day_7_handy_haversacks.py
python_by_contract_corpus/aoc2020/day_8_handheld_halting.py
python_by_contract_corpus/aoc2020/day_9_encoding_error.py
python_by_contract_corpus/ethz_eprog_2019/__init__.py
python_by_contract_corpus/ethz_eprog_2019/exercise_02/__init__.py
python_by_contract_corpus/ethz_eprog_2019/exercise_02/problem_02.py
python_by_contract_corpus/ethz_eprog_2019/exercise_02/problem_03.py
