Metadata-Version: 2.1
Name: python-by-contract-corpus
Version: 2021.7.10rc1
Summary: Provide a corpus of programs annotated with contracts with no obvious bugs.
Home-page: https://github.com/mristin/python-by-contract-corpus
Author: Lauren De bruyn, Marko Ristin, Phillip Schanely
Author-email: marko@ristin.ch
License: License :: OSI Approved :: MIT License
Keywords: design-by-contract contracts automatic testing corpus
Platform: UNKNOWN
Classifier: Development Status :: 5 - Production/Stable
Classifier: License :: OSI Approved :: MIT License
Classifier: Programming Language :: Python :: 3.8
Provides-Extra: dev
